docs/conf.py
intel_sphinx_theme/__init__.py
intel_sphinx_theme/__version__.py
intel_sphinx_theme/link_list.py
intel_sphinx_theme/theme.conf
intel_sphinx_theme/theme.toml
intel_sphinx_theme/themed_image.py
intel_sphinx_theme/static/__init__.py
intel_sphinx_theme/static/favicon.ico
intel_sphinx_theme/static/favicon.svg
intel_sphinx_theme/static/css/spark_sphinx_theme.css
intel_sphinx_theme/static/css/spark_sphinx_theme_tb.css
intel_sphinx_theme/static/css/components/index-tb.css
intel_sphinx_theme/static/css/components/index.css
intel_sphinx_theme/static/css/components/admonitions/index.css
intel_sphinx_theme/static/css/components/admonitions/properties.css
intel_sphinx_theme/static/css/components/admonitions/style.css
intel_sphinx_theme/static/css/components/footer/index.css
intel_sphinx_theme/static/css/components/footer/style.css
intel_sphinx_theme/static/css/components/header/index-tb.css
intel_sphinx_theme/static/css/components/header/index.css
intel_sphinx_theme/static/css/components/header/properties-tb.css
intel_sphinx_theme/static/css/components/header/properties.css
intel_sphinx_theme/static/css/components/header/style-tb.css
intel_sphinx_theme/static/css/components/header/style.css
intel_sphinx_theme/static/css/components/sidebar-primary/index.css
intel_sphinx_theme/static/css/components/sidebar-primary/style.css
intel_sphinx_theme/static/css/components/sidebar-secondary/index.css
intel_sphinx_theme/static/css/components/sidebar-secondary/style.css
intel_sphinx_theme/static/css/components/sphinx-design/button.css
intel_sphinx_theme/static/css/components/sphinx-design/index.css
intel_sphinx_theme/static/css/components/sphinx-design/properties.css
intel_sphinx_theme/static/css/components/table/index.css
intel_sphinx_theme/static/css/components/table/properties.css
intel_sphinx_theme/static/css/components/table/style.css
intel_sphinx_theme/static/css/components/text/index.css
intel_sphinx_theme/static/css/components/text/style.css
intel_sphinx_theme-1.0.1.dist-info/licenses/LICENSE.md
intel_sphinx_theme-1.0.1.dist-info/METADATA
intel_sphinx_theme-1.0.1.dist-info/WHEEL
intel_sphinx_theme-1.0.1.dist-info/entry_points.txt
intel_sphinx_theme-1.0.1.dist-info/top_level.txt
intel_sphinx_theme-1.0.1.dist-info/RECORD
