Metadata-Version: 2.4
Name: intel-sphinx-theme
Version: 1.0.1
Summary: Intel Branded Sphinx Theme
Home-page: https://github.com/intel/intel-sphinx-theme
Author: Intel Corporation
Author-email: 
Maintainer: Erin Olmon, Agustín Francesa
Maintainer-email: erin.olmon@intel.com, agustin.francesa.alfaro@intel.com
License: Apache 2.0
Requires-Python: >=3.5
License-File: LICENSE.md
Requires-Dist: sphinx==7.3.7
Requires-Dist: pydata-sphinx-theme!=0.16.1,~=0.16.0
Requires-Dist: sphinx-copybutton==0.5.0
Requires-Dist: sphinxcontrib-images==0.9.4
Requires-Dist: setuptools
Dynamic: author
Dynamic: description
Dynamic: description-content-type
Dynamic: home-page
Dynamic: license
Dynamic: license-file
Dynamic: maintainer
Dynamic: maintainer-email
Dynamic: requires-dist
Dynamic: requires-python
Dynamic: summary
